pyutils/HDFS.py
pyutils/__init__.py
pyutils/dates.py
pyutils/encodes.py
pyutils/files.py
pyutils/hives.py
pyutils/jsons.py
pyutils/list.py
pyutils/mails.py
pyutils/mysqls.py
pyutils/rediss.py
pyutils/sentrys.py
pyutils/sparks.py
pyutils/sqlservers.py
pyutils/utils.py
pyutils/yamls.py
pyutils/bigdata/HBase.py
pyutils/bigdata/HDFS.py
pyutils/bigdata/__init__.py
pyutils/bigdata/hives.py
pyutils/bigdata/sparks.py
pyutils/bigdata/hbases/__init__.py
pyutils/bigdata/hbases/thrift2/__init__.py
pyutils/bigdata/hbases/thrift2/index.py
pyutils/bigdata/hbases/thrift2/gen-py/__init__.py
pyutils/bigdata/hbases/thrift2/hbase/THBaseService.py
pyutils/bigdata/hbases/thrift2/hbase/__init__.py
pyutils/bigdata/hbases/thrift2/hbase/constants.py
pyutils/bigdata/hbases/thrift2/hbase/ttypes.py
pyutils/database/__init__.py
pyutils/database/mysqls.py
pyutils/database/rediss.py
pyutils/database/sqlservers.py
pyutils/feature/__init__.py
pyutils/feature/encodes.py
pyutils/file/__init__.py
pyutils/file/files.py
pyutils/file/jsons.py
pyutils/file/yamls.py
pyutils/hbases/__init__.py
pyutils/hbases/thrift2/__init__.py
pyutils/hbases/thrift2/index.py
pyutils/hbases/thrift2/gen-py/__init__.py
pyutils/hbases/thrift2/hbase/THBaseService.py
pyutils/hbases/thrift2/hbase/__init__.py
pyutils/hbases/thrift2/hbase/constants.py
pyutils/hbases/thrift2/hbase/ttypes.py
pyutils/recommendation/__init__.py
pyutils/recommendation/dpp/__init__.py
pyutils/recommendation/dpp/dpp.py
pyutils/sparse_engine/__init__.py
pyutils/sparse_engine/base.py
pyutils/sparse_engine/embedding.py
pyutils/sparse_engine/embedding_ops.py
pyutils/time/__init__.py
pyutils/time/dates.py
pyutils/tool/__init__.py
pyutils/tool/list.py
pyutils/tool/mails.py
pyutils/tool/sentrys.py
pyutils/tool/utils.py
rspyutils-0.2.1.4.dist-info/METADATA
rspyutils-0.2.1.4.dist-info/WHEEL
rspyutils-0.2.1.4.dist-info/top_level.txt
rspyutils-0.2.1.4.dist-info/RECORD
