Metadata-Version: 2.1
Name: rspyutils
Version: 0.2.1.4
Summary: An feature extraction algorithm
Home-page: https://github.com/zhanglanhui/pyutils
Author: zhanglanhui
Author-email: zhanglanhui@xndm.tech
License: MIT Licence
Keywords: pip,pyutils,featureextraction
Platform: any
Requires-Dist: PyMySQL
Requires-Dist: pyhdfs
Requires-Dist: pyhive
Requires-Dist: pymssql
Requires-Dist: raven
Requires-Dist: yagmail
Requires-Dist: PyYAML
